bttt99/__init__.py
bttt99/cli.py
bttt99/core.py
bttt99-0.2.1.dist-info/DESCRIPTION.rst
bttt99-0.2.1.dist-info/METADATA
bttt99-0.2.1.dist-info/RECORD
bttt99-0.2.1.dist-info/WHEEL
bttt99-0.2.1.dist-info/entry_points.txt
bttt99-0.2.1.dist-info/metadata.json
bttt99-0.2.1.dist-info/top_level.txt
