Metadata-Version: 2.0
Name: bttt99
Version: 0.2.1
Summary: A tool to navigate movie information.
Home-page: https://github.com/babykick/bttt99
Author: Stephen Chen
Author-email: noemail@noemail.com
License: MIT license
Keywords: bttt99
Platform: UNKNOWN
Classifier: Development Status :: 2 - Pre-Alpha
Classifier: Intended Audience :: Developers
Classifier: License :: OSI Approved :: MIT License
Classifier: Natural Language :: English
Classifier: Programming Language :: Python :: 2
Classifier: Programming Language :: Python :: 2.6
Classifier: Programming Language :: Python :: 2.7
Classifier: Programming Language :: Python :: 3
Classifier: Programming Language :: Python :: 3.3
Classifier: Programming Language :: Python :: 3.4
Classifier: Programming Language :: Python :: 3.5
Requires-Dist: click
Requires-Dist: lxml
Requires-Dist: pyperclip
Requires-Dist: requests
